mds/__init__.py
mds/base.py
mds/huggingface_provider.py
mds/main.py
mds/mcp_service.py
mds/server.py
mds/tools.py
keplore_mds-0.1.1.dist-info/METADATA
keplore_mds-0.1.1.dist-info/WHEEL
keplore_mds-0.1.1.dist-info/entry_points.txt
keplore_mds-0.1.1.dist-info/RECORD
